{
    "name": "Stock",
    "fields": [
        {
            "fieldName": "productCode",
            "fieldType": "String",
            "fieldValidateRules": [
                "required"
            ]
        },
        {
            "fieldName": "supplier",
            "fieldType": "String"
        },
        {
            "fieldName": "quantity",
            "fieldType": "Integer",
            "fieldValidateRules": [
                "required"
            ]
        }
    ],
    "relationships": [],
    "changelogDate": "20181203135304",
    "entityTableName": "stock",
    "dto": "mapstruct",
    "pagination": "infinite-scroll",
    "service": "serviceImpl",
    "jpaMetamodelFiltering": false,
    "fluentMethods": true,
    "clientRootFolder": "",
    "applications": "*"
}